{
  "os": "Windows 10 IoTEnterpriseS 21H2 build 19044",
  "cpu": {
    "name": "AMD Ryzen 7 5800X3D 8-Core Processor",
    "cores": 16,
    "threads": 16,
    "features": []
  },
  "ram": {
    "total_gb": 63.9,
    "free_gb": 0
  },
  "gpu": {
    "gpus": [
      {
        "name": "NVIDIA GeForce RTX 3060 Ti",
        "vendor": "NVIDIA",
        "vram_gb": 8.0
      }
    ],
    "has_nvidia": true,
    "has_amd": false,
    "has_intel": false,
    "has_apple": false,
    "nvidia_driver_version": "595.97",
    "cuda_available": true,
    "cuda_version": "V12.6.20",
    "vulkan_available": true,
    "vulkan_sdk": false,
    "opencl_available": false,
    "rocm_available": false,
    "sycl_available": false,
    "metal_available": false
  },
  "free_disk_gb": 152.9,
  "timestamp": "2026-07-07T20:38:20.452146"
}